Lu_Project_4_C8123/__init__.py
Lu_Project_4_C8123/analysis/ShowResult.py
Lu_Project_4_C8123/analysis/__init__.py
Lu_Project_4_C8123/analysis/drawheatmap.py
Lu_Project_4_C8123/analysis/drow.py
Lu_Project_4_C8123/base/__init__.py
Lu_Project_4_C8123/base/experiment.py
Lu_Project_4_C8123/base/get_dataset.py
Lu_Project_4_C8123/base/get_loss.py
Lu_Project_4_C8123/base/get_metric.py
Lu_Project_4_C8123/base/get_model.py
Lu_Project_4_C8123/base/get_optimizer.py
Lu_Project_4_C8123/base/history.py
Lu_Project_4_C8123/base/metrics.py
Lu_Project_4_C8123/base/models.py
Lu_Project_4_C8123/base/runners.py
Lu_Project_4_C8123/base/tool.py
Lu_Project_4_C8123/main/Main.py
Lu_Project_4_C8123/main/__init__.py
Lu_Project_4_C8123/main/models.py
Lu_Project_4_C8123/main/test.py
Lu_Project_4_C8123/other/__init__.py
Lu_Project_4_C8123/other/count_code_lines.py
Lu_Project_4_C8123/other/tool_dataset_mean_std.py
Lu_Project_4_C8123/other/tool_gen_random_seed.py
Lu_Project_4_C8123/other/uncertain_metrics.py
Lu_Project_4_C8123-0.0.2.dist-info/LICENSE
Lu_Project_4_C8123-0.0.2.dist-info/METADATA
Lu_Project_4_C8123-0.0.2.dist-info/WHEEL
Lu_Project_4_C8123-0.0.2.dist-info/top_level.txt
Lu_Project_4_C8123-0.0.2.dist-info/RECORD
