Metadata-Version: 2.1
Name: Lu-Project-4-C8123
Version: 0.0.2
Summary: A example package for course project
Home-page: https://github.com/pypa/Lu_Project_4_C8123
Author: WangLu
Author-email: p2009842@ipm.edu.mo
License: UNKNOWN
Platform: UNKNOWN
Classifier: Programming Language :: Python :: 3
Classifier: License :: Free For Educational Use
Classifier: Operating System :: OS Independent
